{
    "type": "origins:action_over_time",
    "hidden": true,
    "interval": 20,
    "entity_action": {
        "type": "origins:and",
        "actions": [
			{
                "type": "origins:execute_command",
                "permission_level": 4,
                "command": "team add piglinsx"
            },
            {
                "type": "origins:execute_command",
                "permission_level": 4,
                "command": "team join piglinsx @s"
            },
            {
                "type": "origins:execute_command",
                "permission_level": 4,
                "command": "team join piglinsx @e[type=minecraft:piglin]"
            },
            {
                "type": "origins:execute_command",
                "permission_level": 4,
                "command": "team join piglinsx @e[type=minecraft:piglin_brute]"
            }
        ]
    }
}